metrics/__init__.py
metrics/admin.py
metrics/apps.py
metrics/fields.py
metrics/managers.py
metrics/middleware.py
metrics/models.py
metrics/plugins.py
metrics/router.py
metrics/serializers.py
metrics/settings.py
metrics/traffic.py
metrics/utils.py
metrics/version.py
metrics/locale/de/LC_MESSAGES/django.mo
metrics/locale/de/LC_MESSAGES/django.po
metrics/locale/en/LC_MESSAGES/django.po
metrics/locale/es/LC_MESSAGES/django.mo
metrics/locale/es/LC_MESSAGES/django.po
metrics/locale/fr/LC_MESSAGES/django.mo
metrics/locale/fr/LC_MESSAGES/django.po
metrics/management/__init__.py
metrics/management/commands/__init__.py
metrics/management/commands/purgerequests.py
metrics/migrations/0001_initial.py
metrics/migrations/0002_initial.py
metrics/migrations/0002_remove_request_is_ajax.py
metrics/migrations/0003_update_defaults.py
metrics/migrations/0004_rename_time_to_timestamp.py
metrics/migrations/0005_rename_response_to_status_code.py
metrics/migrations/0006_remove_default_ordering.py
metrics/migrations/0007_resync.py
metrics/migrations/0008_switch_to_big_auto_field.py
metrics/migrations/__init__.py
metrics/static/metrics/js/excanvas.min.js
metrics/static/metrics/js/jquery-3.1.1.min.js
metrics/static/metrics/js/jquery.flot.min.js
metrics/static/metrics/js/jquery.flot.time.min.js
metrics/static/metrics/js/jquery.timeago.js
metrics/static/metrics/js/request.js
metrics/templates/admin/metrics/app_index.html
metrics/templates/metrics/plugins/activeusers.html
metrics/templates/metrics/plugins/base.html
metrics/templates/metrics/plugins/latestrequests.html
metrics/templates/metrics/plugins/table.html
metrics/templates/metrics/plugins/topbrowsers.html
metrics/templates/metrics/plugins/toppaths.html
metrics/templates/metrics/plugins/topreferrers.html
metrics/templates/metrics/plugins/topsearchphrases.html
metrics/templates/metrics/plugins/trafficinformation.html
metrics/templatetags/__init__.py
metrics/templatetags/metrics_admin.py
metrics/templatetags/metrics_tag.py
django_site_metrics-0.1.3.dist-info/LICENSE
django_site_metrics-0.1.3.dist-info/METADATA
django_site_metrics-0.1.3.dist-info/WHEEL
django_site_metrics-0.1.3.dist-info/top_level.txt
django_site_metrics-0.1.3.dist-info/RECORD
