Metadata-Version: 2.1
Name: django-site-metrics
Version: 0.1.3
Summary: django-site-metrics is a statistics module for django. It stores requests in a database for admins to see, it can also be used to get statistics on who is online etc.
Requires-Dist: Django (>=2.2)
Requires-Dist: python-dateutil
